accern_data/__init__.py
accern_data/__main__.py
accern_data/accern_data.py
accern_data/py.typed
accern_data/util.py
accern_data-0.2.1.data/data/accern_data/data-2022.csv
accern_data-0.2.1.data/data/accern_data/data-2022.json
accern_data-0.2.1.dist-info/LICENSE
accern_data-0.2.1.dist-info/METADATA
accern_data-0.2.1.dist-info/WHEEL
accern_data-0.2.1.dist-info/top_level.txt
accern_data-0.2.1.dist-info/RECORD
