Metadata-Version: 2.1
Name: accern-data
Version: 0.2.1
Summary: Client for consuming Accern data feeds.
Home-page: https://github.com/Accern/accern-data-client
Author: Accern Corp.
Author-email: datascience@accern.com
License: MIT
Keywords: api client data feed NLP processing
Classifier: Development Status :: 4 - Beta
Classifier: License :: OSI Approved :: MIT License
Classifier: Operating System :: OS Independent
Classifier: Programming Language :: Python :: 3.7
Classifier: Programming Language :: Python :: 3.8
Classifier: Programming Language :: Python :: 3.9
Classifier: Programming Language :: Python :: 3
Requires-Python: >=3.7.1
License-File: LICENSE
Requires-Dist: pandas (>=1.3.0)
Requires-Dist: requests (>=2.27.1)
Requires-Dist: tqdm (>=4.64.0)
Requires-Dist: typing-extensions (>=4.3.0)
Provides-Extra: jupyter
Requires-Dist: ipywidgets ; extra == 'jupyter'
